adsb/__init__.py
adsb/version.py
adsb/version.txt
ads_b-0.0.1.dist-info/LICENSE
ads_b-0.0.1.dist-info/METADATA
ads_b-0.0.1.dist-info/WHEEL
ads_b-0.0.1.dist-info/top_level.txt
ads_b-0.0.1.dist-info/RECORD
